GenWoYiqiXieBianyiqi/README.md
GenWoYiqiXieBianyiqi/__init__.py
GenWoYiqiXieBianyiqi/__main__.py
GenWoYiqiXieBianyiqi/file.epub
GenWoYiqiXieBianyiqi/index.html
GenWoYiqiXieBianyiqi/css/__init__.py
GenWoYiqiXieBianyiqi/css/annotations.css
GenWoYiqiXieBianyiqi/css/main.css
GenWoYiqiXieBianyiqi/css/normalize.css
GenWoYiqiXieBianyiqi/css/popup.css
GenWoYiqiXieBianyiqi/font/__init__.py
GenWoYiqiXieBianyiqi/font/fontello.eot
GenWoYiqiXieBianyiqi/font/fontello.svg
GenWoYiqiXieBianyiqi/font/fontello.ttf
GenWoYiqiXieBianyiqi/font/fontello.woff
GenWoYiqiXieBianyiqi/img/__init__.py
GenWoYiqiXieBianyiqi/img/annotator-glyph-sprite.png
GenWoYiqiXieBianyiqi/img/annotator-icon-sprite.png
GenWoYiqiXieBianyiqi/img/apple-touch-icon.png
GenWoYiqiXieBianyiqi/img/cancelfullscreen.png
GenWoYiqiXieBianyiqi/img/close.png
GenWoYiqiXieBianyiqi/img/fullscreen.png
GenWoYiqiXieBianyiqi/img/loader.gif
GenWoYiqiXieBianyiqi/img/menu-icon.png
GenWoYiqiXieBianyiqi/img/save.png
GenWoYiqiXieBianyiqi/img/saved.png
GenWoYiqiXieBianyiqi/img/settings-s.png
GenWoYiqiXieBianyiqi/img/settings.png
GenWoYiqiXieBianyiqi/img/star.png
GenWoYiqiXieBianyiqi/js/__init__.py
GenWoYiqiXieBianyiqi/js/epub.js
GenWoYiqiXieBianyiqi/js/epub.min.js
GenWoYiqiXieBianyiqi/js/epub.min.map
GenWoYiqiXieBianyiqi/js/hooks.min.js
GenWoYiqiXieBianyiqi/js/hooks.min.map
GenWoYiqiXieBianyiqi/js/reader.js
GenWoYiqiXieBianyiqi/js/reader.js.map
GenWoYiqiXieBianyiqi/js/reader.min.js
GenWoYiqiXieBianyiqi/js/reader.min.map
GenWoYiqiXieBianyiqi/js/hooks/__init__.py
GenWoYiqiXieBianyiqi/js/hooks/extensions/__init__.py
GenWoYiqiXieBianyiqi/js/hooks/extensions/highlight.js
GenWoYiqiXieBianyiqi/js/libs/__init__.py
GenWoYiqiXieBianyiqi/js/libs/jquery.min.js
GenWoYiqiXieBianyiqi/js/libs/localforage.min.js
GenWoYiqiXieBianyiqi/js/libs/screenfull.js
GenWoYiqiXieBianyiqi/js/libs/screenfull.min.js
GenWoYiqiXieBianyiqi/js/libs/zip.min.js
GenWoYiqiXieBianyiqi/js/plugins/__init__.py
GenWoYiqiXieBianyiqi/js/plugins/hypothesis.js
gen_wo_yiqi_xie_bianyiqi-2024.3.6.0.dist-info/METADATA
gen_wo_yiqi_xie_bianyiqi-2024.3.6.0.dist-info/WHEEL
gen_wo_yiqi_xie_bianyiqi-2024.3.6.0.dist-info/entry_points.txt
gen_wo_yiqi_xie_bianyiqi-2024.3.6.0.dist-info/top_level.txt
gen_wo_yiqi_xie_bianyiqi-2024.3.6.0.dist-info/RECORD
